tests/__init__.py
uniqcharstest6-1.0.dist-info/LICENSE
uniqcharstest6-1.0.dist-info/METADATA
uniqcharstest6-1.0.dist-info/WHEEL
uniqcharstest6-1.0.dist-info/entry_points.txt
uniqcharstest6-1.0.dist-info/top_level.txt
uniqcharstest6-1.0.dist-info/RECORD
