Metadata-Version: 2.1
Name: uniqcharstest6
Version: 1.0
Summary: Count of uniq chars in string package
Home-page: UNKNOWN
Author: Dihtiar Vadym
License: UNKNOWN
Platform: UNKNOWN
Requires-Python: >=3.8
License-File: LICENSE
Requires-Dist: pytest (==7.2.0)
